distkv_ext/hass/__init__.py
distkv_ext/hass/client.py
distkv_hass-0.4.0.dist-info/METADATA
distkv_hass-0.4.0.dist-info/WHEEL
distkv_hass-0.4.0.dist-info/top_level.txt
distkv_hass-0.4.0.dist-info/zip-safe
distkv_hass-0.4.0.dist-info/RECORD
